abugida/SERA_table.json
abugida/__init__.py
abugida/convert_calendar.py
abugida/convert_numeral.py
abugida/convert_script.py
tests/__init__.py
tests/calendar_conversion_test.py
tests/numeral_conversion_test.py
tests/script_conversion_test.py
abugida-0.3.4.dist-info/LICENSE
abugida-0.3.4.dist-info/METADATA
abugida-0.3.4.dist-info/WHEEL
abugida-0.3.4.dist-info/top_level.txt
abugida-0.3.4.dist-info/RECORD
