Metadata-Version: 2.1
Name: abugida
Version: 0.3.4
Summary: NLP tools and resources for Ethiopian languages
Project-URL: Source, https://github.com/hadamard-2/abugidanlp
Keywords: nlp,ethiopian languages,ethiopic,abugida,ge'ez
Classifier: Intended Audience :: Developers
Classifier: Programming Language :: Python :: 3
Classifier: Operating System :: OS Independent
Classifier: License :: OSI Approved :: MIT License
License-File: LICENSE
